magnum/__init__.py
magnum/i18n.py
magnum/version.py
magnum/api/__init__.py
magnum/api/app.py
magnum/api/attr_validator.py
magnum/api/config.py
magnum/api/expose.py
magnum/api/hooks.py
magnum/api/http_error.py
magnum/api/rest_api_version_history.rst
magnum/api/servicegroup.py
magnum/api/utils.py
magnum/api/validation.py
magnum/api/versioned_method.py
magnum/api/controllers/__init__.py
magnum/api/controllers/base.py
magnum/api/controllers/link.py
magnum/api/controllers/root.py
magnum/api/controllers/versions.py
magnum/api/controllers/v1/__init__.py
magnum/api/controllers/v1/certificate.py
magnum/api/controllers/v1/cluster.py
magnum/api/controllers/v1/cluster_actions.py
magnum/api/controllers/v1/cluster_template.py
magnum/api/controllers/v1/collection.py
magnum/api/controllers/v1/credential.py
magnum/api/controllers/v1/federation.py
magnum/api/controllers/v1/magnum_services.py
magnum/api/controllers/v1/nodegroup.py
magnum/api/controllers/v1/quota.py
magnum/api/controllers/v1/stats.py
magnum/api/controllers/v1/types.py
magnum/api/middleware/__init__.py
magnum/api/middleware/auth_token.py
magnum/api/middleware/parsable_error.py
magnum/cmd/__init__.py
magnum/cmd/api.py
magnum/cmd/conductor.py
magnum/cmd/db_manage.py
magnum/cmd/driver_manage.py
magnum/cmd/status.py
magnum/common/__init__.py
magnum/common/cinder.py
magnum/common/clients.py
magnum/common/config.py
magnum/common/context.py
magnum/common/exception.py
magnum/common/keystone.py
magnum/common/name_generator.py
magnum/common/neutron.py
magnum/common/nova.py
magnum/common/octavia.py
magnum/common/policy.py
magnum/common/profiler.py
magnum/common/rpc.py
magnum/common/rpc_service.py
magnum/common/service.py
magnum/common/short_id.py
magnum/common/urlfetch.py
magnum/common/utils.py
magnum/common/cert_manager/__init__.py
magnum/common/cert_manager/barbican_cert_manager.py
magnum/common/cert_manager/cert_manager.py
magnum/common/cert_manager/local_cert_manager.py
magnum/common/cert_manager/x509keypair_cert_manager.py
magnum-21.0.1.dist-info/AUTHORS
magnum-21.0.1.dist-info/LICENSE
magnum-21.0.1.dist-info/METADATA
magnum-21.0.1.dist-info/WHEEL
magnum-21.0.1.dist-info/entry_points.txt
magnum-21.0.1.dist-info/pbr.json
magnum-21.0.1.dist-info/top_level.txt
magnum-21.0.1.dist-info/RECORD
